scDistRank/__init__.py
scDistRank/searchOptimal.py
scDistRank/visualization.py
scdistrank-0.0.0.3.dist-info/METADATA
scdistrank-0.0.0.3.dist-info/WHEEL
scdistrank-0.0.0.3.dist-info/RECORD
