Metadata-Version: 2.3
Name: scDistRank
Version: 0.0.0.3
Summary: Separate your clusters with gene distance
Project-URL: Homepage, https://github.com/brocklab/scDistRank
Project-URL: Issues, https://github.com/brocklab/scDistRank/issues
Author-email: Tyler Jost <tyler_jost@utexas.edu>
Classifier: License :: OSI Approved :: MIT License
Classifier: Operating System :: OS Independent
Classifier: Programming Language :: Python :: 3
Requires-Python: >=3.8
Requires-Dist: matplotlib>=3.8
Requires-Dist: numpy>=1.26.3
Requires-Dist: pandas>=2.2.0
Requires-Dist: scanpy>=1.9.8
Requires-Dist: scipy>=1.12.0
Requires-Dist: seaborn>=0.13.2
Requires-Dist: tqdm>=4.66.1
